ai_models/__init__.py
ai_models/__main__.py
ai_models/ai_tools.py
ai_models/audio_to_text.py
ai_models/image_classification.py
ai_models/llm.py
ai_models/named_entity_recognition.py
ai_models/object_detection.py
ai_models/question_answering.py
ai_models/sentiment_analysis.py
ai_models/text_classification.py
ai_models/text_comparison.py
ai_models/text_extraction.py
ai_models/text_summarization.py
ai_models/text_translation.py
4th_ir_ai_models-0.5.3.dist-info/LICENSE
4th_ir_ai_models-0.5.3.dist-info/METADATA
4th_ir_ai_models-0.5.3.dist-info/WHEEL
4th_ir_ai_models-0.5.3.dist-info/top_level.txt
4th_ir_ai_models-0.5.3.dist-info/RECORD
