Metadata-Version: 2.1
Name: 4th-ir-ai-models
Version: 0.5.3
Summary: Access a collection of sophisticated AI models.
Author-email: 4th-IR <a.toffah@4th-ir.com>
License: MIT License
Project-URL: Homepage, https://www.4th-ir.com/
Keywords: ai,api,automation,ai tool,intelligence
Classifier: License :: OSI Approved :: MIT License
Classifier: Operating System :: OS Independent
Classifier: Programming Language :: Python :: 3
Requires-Python: >=3.8
License-File: LICENSE
Requires-Dist: requests >=2.32.3
